idendrogram/__init__.py
idendrogram/base.py
idendrogram/callbacks.py
idendrogram/clustering_data.py
idendrogram/containers.py
idendrogram/targets/__init__.py
idendrogram/targets/altair.py
idendrogram/targets/common.py
idendrogram/targets/json.py
idendrogram/targets/matplotlib.py
idendrogram/targets/plotly.py
idendrogram/targets/streamlit.py
idendrogram-0.2.0.dist-info/LICENSE
idendrogram-0.2.0.dist-info/WHEEL
idendrogram-0.2.0.dist-info/METADATA
idendrogram-0.2.0.dist-info/RECORD
