Metadata-Version: 2.1
Name: idendrogram
Version: 0.2.0
Summary: Interactive dendrograms compatible with scipy, scikit-learn and hdbscan
Keywords: dendrogram,hierarchical clustering,clustering
Author: Aurimas Racas
Requires-Python: >=3.8
Classifier: Programming Language :: Python :: 3
Classifier: License :: OSI Approved :: MIT License
Classifier: Operating System :: OS Independent
Requires-Dist: scipy >= 1.8.0
Requires-Dist: numpy >= 1.22.0
Requires-Dist: matplotlib ; extra == "full"
Requires-Dist: altair>=1.4.2 ; extra == "full"
Requires-Dist: plotly ; extra == "full"
Requires-Dist: hdbscan ; extra == "full"
Requires-Dist: scikit-learn ; extra == "full"
Requires-Dist: pandas ; extra == "full"
Requires-Dist: streamlit ; extra == "streamlit"
Project-URL: Documentation, https://github.com/kamicollo/idendrogram
Project-URL: Home, https://github.com/kamicollo/idendrogram
Provides-Extra: full
Provides-Extra: streamlit
